flowjs/__init__.py
flowjs/config.py
flowjs/file.py
flowjs/interfaces.py
flowjs/requests.py
flowjs-0.1.1.dist-info/METADATA
flowjs-0.1.1.dist-info/RECORD
flowjs-0.1.1.dist-info/WHEEL
flowjs-0.1.1.dist-info/top_level.txt
