Metadata-Version: 2.1
Name: flowjs
Version: 0.1.1
Summary: Python server implementation for flow.js upload library
Home-page: https://github.com/huwcbjones/py-flowjs
Author: Huw Jones
Author-email: huwcbjones@gmail.com
License: MIT License
Requires-Dist: filelock
